juntagrico_calendar/__init__.py
juntagrico_calendar/apps.py
juntagrico_calendar/urls.py
juntagrico_calendar/views.py
juntagrico_calendar/static/css/jobcalendar.css
juntagrico_calendar/static/external/fullcalendar/bootstrap/main.min.css
juntagrico_calendar/static/external/fullcalendar/bootstrap/main.min.js
juntagrico_calendar/static/external/fullcalendar/core/main.min.css
juntagrico_calendar/static/external/fullcalendar/core/main.min.js
juntagrico_calendar/static/external/fullcalendar/core/locales/de.js
juntagrico_calendar/static/external/fullcalendar/daygrid/main.min.css
juntagrico_calendar/static/external/fullcalendar/daygrid/main.min.js
juntagrico_calendar/static/external/fullcalendar/list/main.min.css
juntagrico_calendar/static/external/fullcalendar/list/main.min.js
juntagrico_calendar/static/js/jobcalendar.js
juntagrico_calendar/templates/cal/job_calendar.html
juntagrico_calendar/templates/cal/snippets/content_snippet.html
juntagrico_calendar/templates/cal/snippets/scripts_snippet.html
juntagrico_calendar/templates/cal/snippets/styles_snippet.html
juntagrico_calendar/util/__init__.py
juntagrico_calendar/util/temporal.py
juntagrico_calendar-1.6.0.dist-info/LICENSE
juntagrico_calendar-1.6.0.dist-info/METADATA
juntagrico_calendar-1.6.0.dist-info/WHEEL
juntagrico_calendar-1.6.0.dist-info/top_level.txt
juntagrico_calendar-1.6.0.dist-info/RECORD
