Metadata-Version: 2.1
Name: juntagrico-calendar
Version: 1.6.0
Summary: Show jobs as calendar or agenda
Author-email: juntagrico <python@juntagrico.org>
License: GNU LESSER GENERAL PUBLIC LICENSE
Project-URL: Homepage, https://www.juntagrico.org
Project-URL: Issues, https://github.com/mehalsgmues/juntagrico_calendar/issues
Project-URL: Changelog, https://github.com/mehalsgmues/juntagrico_calendar/releases
Classifier: Development Status :: 5 - Production/Stable
Classifier: Environment :: Web Environment
Classifier: Framework :: Django
Classifier: Framework :: Django :: 4.2
Classifier: Intended Audience :: Developers
Classifier: Intended Audience :: Other Audience
Classifier: License :: OSI Approved :: GNU Lesser General Public License v3 (LGPLv3)
Classifier: Operating System :: OS Independent
Classifier: Programming Language :: Python
Classifier: Programming Language :: Python :: 3.8
Classifier: Programming Language :: Python :: 3.9
Classifier: Programming Language :: Python :: 3.10
Classifier: Programming Language :: Python :: 3.11
Classifier: Topic :: Internet :: WWW/HTTP :: Site Management
Requires-Python: >=3.8
License-File: LICENSE
Requires-Dist: juntagrico >=1.6.0
Requires-Dist: iso8601 <2.0,>=1.0.2
